Metadata-Version: 2.1
Name: notion-dashworks-fork
Version: 0.0.7
Summary: Unofficial Python API client for Notion.so forked for dashworks
Home-page: https://github.com/dashworkstech/notion-dashworks
Author: Developers Dashworks
Author-email: support@dashworks.ai
License: UNKNOWN
Platform: UNKNOWN
Classifier: Programming Language :: Python :: 3
Classifier: License :: OSI Approved :: MIT License
Classifier: Operating System :: OS Independent
Requires-Python: >=3.9
Requires-Dist: requests
Requires-Dist: commonmark
Requires-Dist: bs4
Requires-Dist: tzlocal
Requires-Dist: python-slugify
Requires-Dist: dictdiffer
Requires-Dist: cached-property
